pygments_httpie/__init__.py
pygments_httpie/http.py
pygments_httpie/httpie.py
pygments_httpie-0.1.dist-info/LICENSE
pygments_httpie-0.1.dist-info/METADATA
pygments_httpie-0.1.dist-info/WHEEL
pygments_httpie-0.1.dist-info/entry_points.txt
pygments_httpie-0.1.dist-info/top_level.txt
pygments_httpie-0.1.dist-info/RECORD
